{"description": "Specify the size component of the rekey limit. This limit signifies amount\nof data. After this amount of data is transferred through the connection,\nthe session key is renegotiated. The number is followed by K, M or G for\nkilobytes, megabytes or gigabytes. Note that the RekeyLimit can be also\nconfigured according to elapsed time.", "type": "string", "operator": "equals", "interactive": true, "options": {"default": "512M", "512M": "512M", "1G": "1G"}, "warnings": [], "title": "SSH client RekeyLimit - size", "definition_location": "/home/greek_fire/.git/content/linux_os/guide/system/software/integrity/crypto/var_ssh_client_rekey_limit_size.var"}