{"description": "If the system does not need to operate as an IMAP or\nPOP3 server, the dovecot software should be disabled and removed.", "warnings": [], "requires": [], "conflicts": [], "values": {}, "groups": {}, "rules": ["package_dovecot_removed", "service_dovecot_disabled"], "platform": "", "platforms": [], "inherited_platforms": [], "cpe_platform_names": [], "title": "Disable Dovecot", "definition_location": "/home/greek_fire/.git/content/linux_os/guide/services/imap/disabling_dovecot/group.yml"}