{"description": "Users must not be allowed to access the shell programs.", "rationale": "Shell programs might execute shell escapes and could then perform\nunauthorized activities that could damage the security posture of the web\nserver. A shell is a program that serves as the basic interface between the\nuser and the operating system. In this regard, there are shells that are\nsecurity risks in the context of a web server and shells that are\nunauthorized.", "severity": "medium", "references": {}, "control_references": {}, "components": ["httpd"], "identifiers": {}, "ocil_clause": "either of these exist and they configure csh, or any other shell as a viewer for documents", "ocil": "Enter the following commands:\n\n<pre><tt>grep Action /etc/httpd/conf/httpd.conf</tt>\n<tt>grep AddHandler /etc/httpd/conf/httpd.conf</tt></pre>", "oval_external_content": null, "fixtext": "", "checktext": "", "vuldiscussion": "", "srg_requirement": "", "warnings": [], "conflicts": [], "requires": [], "policy_specific_content": {}, "platform": null, "platforms": [], "sce_metadata": {}, "inherited_platforms": [], "cpe_platform_names": [], "inherited_cpe_platform_names": [], "bash_conditional": null, "fixes": {}, "check_type": null, "inputs": [], "expression": null, "failure_reason": null, "title": "MIME types for csh or sh shell programs must be disabled", "definition_location": "/home/greek_fire/.git/content/linux_os/guide/services/http/securing_httpd/httpd_disable_mime_types/rule.yml", "template": null}